grscheller/datastructures/__init__.py
grscheller/datastructures/nodes.py
grscheller/datastructures/py.typed
grscheller/datastructures/queues.py
grscheller/datastructures/tuples.py
grscheller/datastructures/splitends/__init__.py
grscheller/datastructures/splitends/py.typed
grscheller/datastructures/splitends/se.py
grscheller_datastructures-0.24.0.dist-info/LICENSE
grscheller_datastructures-0.24.0.dist-info/WHEEL
grscheller_datastructures-0.24.0.dist-info/METADATA
grscheller_datastructures-0.24.0.dist-info/RECORD
