Metadata-Version: 2.3
Name: grscheller.datastructures
Version: 0.24.0
Summary: ### package datastructures
Keywords: datastructures,data structures,fifo,lifo,stack,queue,SplitEnd
Author-email: "Geoffrey R. Scheller" <geoffrey@scheller.com>
Requires-Python: >=3.12
Classifier: Development Status :: 4 - Beta
Classifier: Framework :: Pytest
Classifier: Intended Audience :: Developers
Classifier: License :: OSI Approved :: Apache Software License
Classifier: Operating System :: OS Independent
Classifier: Programming Language :: Python :: 3.13
Classifier: Typing :: Typed
Requires-Dist: grscheller.circular-array >= 3.8.1, < 3.9
Requires-Dist: grscheller.fp >= 1.2.0, < 1.3
Requires-Dist: pytest >=8.3.2 ; extra == "test"
Project-URL: Changelog, https://github.com/grscheller/datastructures/blob/main/CHANGELOG.md
Project-URL: Documentation, https://grscheller.github.io/grscheller-pypi-namespace-docs/datastructures
Project-URL: Source, https://github.com/grscheller/datastructures
Provides-Extra: test
